cengal_memory_barriers/__init__.py
cengal_memory_barriers-2.1.0.dist-info/METADATA
cengal_memory_barriers-2.1.0.dist-info/WHEEL
cengal_memory_barriers-2.1.0.dist-info/licenses/LICENSE.md
cengal_memory_barriers-2.1.0.dist-info/licenses/NOTICE
cengal_memory_barriers-2.1.0.dist-info/RECORD
